LICENSE
README.md
docs/Makefile
docs/build/doctrees/acknowledgments.doctree
docs/build/doctrees/awknowledgements.doctree
docs/build/doctrees/core_components.doctree
docs/build/doctrees/dependencies.doctree
docs/build/doctrees/environment.pickle
docs/build/doctrees/examples.doctree
docs/build/doctrees/index.doctree
docs/build/doctrees/installation.doctree
docs/build/doctrees/knitout_interpreter.doctree
docs/build/doctrees/knitout_interpreter.knitout_execution.doctree
docs/build/doctrees/knitout_interpreter.knitout_execution_structures.Carriage_Pass.doctree
docs/build/doctrees/knitout_interpreter.knitout_execution_structures.doctree
docs/build/doctrees/knitout_interpreter.knitout_language.Knitout_Context.doctree
docs/build/doctrees/knitout_interpreter.knitout_language.Knitout_Parser.doctree
docs/build/doctrees/knitout_interpreter.knitout_language.doctree
docs/build/doctrees/knitout_interpreter.knitout_language.knitout_actions.doctree
docs/build/doctrees/knitout_interpreter.knitout_operations.Header_Line.doctree
docs/build/doctrees/knitout_interpreter.knitout_operations.Knitout_Line.doctree
docs/build/doctrees/knitout_interpreter.knitout_operations.Pause_Instruction.doctree
docs/build/doctrees/knitout_interpreter.knitout_operations.Rack_Instruction.doctree
docs/build/doctrees/knitout_interpreter.knitout_operations.carrier_instructions.doctree
docs/build/doctrees/knitout_interpreter.knitout_operations.doctree
docs/build/doctrees/knitout_interpreter.knitout_operations.kick_instruction.doctree
docs/build/doctrees/knitout_interpreter.knitout_operations.knitout_instruction.doctree
docs/build/doctrees/knitout_interpreter.knitout_operations.knitout_instruction_factory.doctree
docs/build/doctrees/knitout_interpreter.knitout_operations.needle_instructions.doctree
docs/build/doctrees/knitout_interpreter.run_knitout.doctree
docs/build/doctrees/modules.doctree
docs/build/doctrees/quickstart.doctree
docs/build/doctrees/related_projects.doctree
docs/build/html/.buildinfo
knitout_interpreter-0.1.2.dist-info/LICENSE
knitout_interpreter-0.1.2.dist-info/METADATA
knitout_interpreter-0.1.2.dist-info/WHEEL
knitout_interpreter-0.1.2.dist-info/RECORD
