Metadata-Version: 2.1
Name: knitout-interpreter
Version: 0.1.2
Summary: Support for interpreting knitout files used for controlling automatic V-Bed Knitting machines.
Home-page: https://mhofmann-khoury.github.io/knitout_interpreter/
License: MIT
Keywords: knit,machine knit,textile,Northeastern,ACT Lab,fabrication,knitout
Author: Megan Hofmann
Author-email: m.hofmann@northeastern.edu
Maintainer: Megan Hofmann
Maintainer-email: m.hofmann@northeastern.edu
Requires-Python: >=3.11,<3.14
Classifier: Development Status :: 2 - Pre-Alpha
Classifier: Intended Audience :: Developers
Classifier: Intended Audience :: Manufacturing
Classifier: License :: OSI Approved :: MIT License
Classifier: Natural Language :: English
Classifier: Operating System :: OS Independent
Classifier: Programming Language :: Python :: 3
Classifier: Programming Language :: Python :: 3.11
Classifier: Programming Language :: Python :: 3.12
Classifier: Programming Language :: Python :: 3.13
Classifier: Topic :: Scientific/Engineering
Classifier: Typing :: Typed
Requires-Dist: importlib_resources (>=6.5)
Requires-Dist: knit-graphs (>=0.0.11)
Requires-Dist: parglare (>=0.19.0,<0.20.0)
Requires-Dist: virtual-knitting-machine (>=0.0.22)
Project-URL: Documentation, https://mhofmann-khoury.github.io/knitout_interpreter/
Project-URL: Repository, https://github.com/mhofmann-Khoury/knitout_interpreter
